abstractllm/CLAUDE.md
abstractllm/__init__.py
abstractllm/cli.py
abstractllm/enums.py
abstractllm/exceptions.py
abstractllm/factory.py
abstractllm/interface.py
abstractllm/memory.py
abstractllm/retry_strategies.py
abstractllm/scratchpad_manager.py
abstractllm/session.py
abstractllm/structured_response.py
abstractllm/types.py
abstractllm/architectures/CLAUDE.md
abstractllm/architectures/__init__.py
abstractllm/architectures/detection.py
abstractllm/architectures/enums.py
abstractllm/assets/CLAUDE.md
abstractllm/assets/architecture_formats.json
abstractllm/assets/model_capabilities.json
abstractllm/cognitive/__init__.py
abstractllm/cognitive/auto_enhance.py
abstractllm/cognitive/base.py
abstractllm/cognitive/examples.py
abstractllm/cognitive/facts_extractor.py
abstractllm/cognitive/patch_facts.py
abstractllm/cognitive/semantic_extractor.py
abstractllm/cognitive/summarizer.py
abstractllm/cognitive/value_resonance.py
abstractllm/cognitive/integrations/__init__.py
abstractllm/cognitive/integrations/memory_integration.py
abstractllm/cognitive/integrations/session_integration.py
abstractllm/cognitive/prompts/__init__.py
abstractllm/cognitive/prompts/facts_prompts.py
abstractllm/cognitive/prompts/summarizer_prompts.py
abstractllm/cognitive/prompts/values_prompts.py
abstractllm/media/CLAUDE.md
abstractllm/media/__init__.py
abstractllm/media/factory.py
abstractllm/media/image.py
abstractllm/media/interface.py
abstractllm/media/processor.py
abstractllm/media/tabular.py
abstractllm/media/text.py
abstractllm/providers/CLAUDE.md
abstractllm/providers/__init__.py
abstractllm/providers/anthropic.py
abstractllm/providers/base.py
abstractllm/providers/huggingface.py
abstractllm/providers/lmstudio_provider.py
abstractllm/providers/migration_status.py
abstractllm/providers/mlx_model_configs.py
abstractllm/providers/mlx_provider.py
abstractllm/providers/ollama.py
abstractllm/providers/openai.py
abstractllm/providers/registry.py
abstractllm/providers/huggingface/CLAUDE.md
abstractllm-1.1.5.dist-info/METADATA
abstractllm-1.1.5.dist-info/WHEEL
abstractllm-1.1.5.dist-info/entry_points.txt
abstractllm-1.1.5.dist-info/licenses/LICENSE
abstractllm-1.1.5.dist-info/RECORD
