Metadata-Version: 2.4
Name: abstractllm
Version: 1.1.5
Summary: A unified interface for large language models with support for OpenAI, Anthropic, Hugging Face, Ollama, and MLX
Project-URL: Homepage, https://github.com/lpalbou/abstractllm
Project-URL: Repository, https://github.com/lpalbou/abstractllm.git
Project-URL: Bug Tracker, https://github.com/lpalbou/abstractllm/issues
Author-email: Laurent-Philippe Albou <lpalbou@gmail.com>
License-Expression: MIT
License-File: LICENSE
Keywords: abstraction,ai,apple silicon,claude,gpt,huggingface,llm,mlx,ollama,openai
Classifier: Development Status :: 3 - Alpha
Classifier: Intended Audience :: Developers
Classifier: License :: OSI Approved :: MIT License
Classifier: Operating System :: MacOS :: MacOS X
Classifier: Operating System :: Microsoft :: Windows
Classifier: Operating System :: POSIX :: Linux
Classifier: Programming Language :: Python :: 3
Classifier: Programming Language :: Python :: 3.8
Classifier: Programming Language :: Python :: 3.9
Classifier: Programming Language :: Python :: 3.10
Classifier: Programming Language :: Python :: 3.11
Requires-Python: >=3.8
Requires-Dist: pillow>=9.0.0
Requires-Dist: pydantic>=2.0.0
Requires-Dist: typing-extensions>=4.0.0
Provides-Extra: all
Requires-Dist: aiohttp>=3.8.0; extra == 'all'
Requires-Dist: anthropic>=0.18.0; extra == 'all'
Requires-Dist: docstring-parser>=0.15; extra == 'all'
Requires-Dist: huggingface-hub>=0.20.0; extra == 'all'
Requires-Dist: humanize>=4.6.0; extra == 'all'
Requires-Dist: jsonschema>=4.0.0; extra == 'all'
Requires-Dist: mlx-lm>=0.0.7; extra == 'all'
Requires-Dist: mlx>=0.0.25; extra == 'all'
Requires-Dist: numpy>=1.24.0; extra == 'all'
Requires-Dist: openai>=1.0.0; extra == 'all'
Requires-Dist: pillow>=9.0.0; extra == 'all'
Requires-Dist: pydantic>=2.0.0; extra == 'all'
Requires-Dist: requests>=2.25.0; extra == 'all'
Requires-Dist: torch>=2.0.0; extra == 'all'
Requires-Dist: transformers>=4.36.0; extra == 'all'
Provides-Extra: anthropic
Requires-Dist: anthropic>=0.18.0; extra == 'anthropic'
Provides-Extra: dev
Requires-Dist: black>=23.0.0; extra == 'dev'
Requires-Dist: isort>=5.0.0; extra == 'dev'
Requires-Dist: pytest-cov>=4.0.0; extra == 'dev'
Requires-Dist: pytest>=7.0.0; extra == 'dev'
Provides-Extra: huggingface
Requires-Dist: huggingface-hub>=0.20.0; extra == 'huggingface'
Requires-Dist: pillow>=9.0.0; extra == 'huggingface'
Requires-Dist: torch>=2.0.0; extra == 'huggingface'
Requires-Dist: transformers>=4.36.0; extra == 'huggingface'
Provides-Extra: mlx
Requires-Dist: huggingface-hub>=0.15.0; extra == 'mlx'
Requires-Dist: humanize>=4.6.0; extra == 'mlx'
Requires-Dist: mlx-lm>=0.0.7; extra == 'mlx'
Requires-Dist: mlx>=0.0.25; extra == 'mlx'
Requires-Dist: numpy>=1.24.0; extra == 'mlx'
Requires-Dist: pillow>=9.0.0; extra == 'mlx'
Requires-Dist: transformers>=4.30.0; extra == 'mlx'
Provides-Extra: ollama
Requires-Dist: aiohttp>=3.8.0; extra == 'ollama'
Requires-Dist: requests>=2.25.0; extra == 'ollama'
Provides-Extra: openai
Requires-Dist: openai>=1.0.0; extra == 'openai'
Provides-Extra: tools
Requires-Dist: docstring-parser>=0.15; extra == 'tools'
Requires-Dist: jsonschema>=4.0.0; extra == 'tools'
Requires-Dist: pydantic>=2.0.0; extra == 'tools'
